cfn_model/__init__.py
cfn_model/model/CfnModel.py
cfn_model/model/EC2Instance.py
cfn_model/model/EC2NetworkInterface.py
cfn_model/model/EC2SecurityGroup.py
cfn_model/model/EC2SecurityGroupEgress.py
cfn_model/model/EC2SecurityGroupIngress.py
cfn_model/model/ElasticLoadBalancingLoadBalancer.py
cfn_model/model/ElasticLoadBalancingV2LoadBalancer.py
cfn_model/model/IAMGroup.py
cfn_model/model/IAMManagedPolicy.py
cfn_model/model/IAMPolicy.py
cfn_model/model/IAMRole.py
cfn_model/model/IAMUser.py
cfn_model/model/LambdaPrincipal.py
cfn_model/model/ModelElement.py
cfn_model/model/Parameter.py
cfn_model/model/Policy.py
cfn_model/model/PolicyDocument.py
cfn_model/model/Principal.py
cfn_model/model/References.py
cfn_model/model/S3BucketPolicy.py
cfn_model/model/SNSTopicPolicy.py
cfn_model/model/SQSQueuePolicy.py
cfn_model/model/Statement.py
cfn_model/model/__init__.py
cfn_model/parser/CfnParser.py
cfn_model/parser/Ec2InstanceParser.py
cfn_model/parser/Ec2NetworkInterfaceParser.py
cfn_model/parser/Error.py
cfn_model/parser/IamGroupParser.py
cfn_model/parser/IamRoleParser.py
cfn_model/parser/IamUserParser.py
cfn_model/parser/LoadBalancerParser.py
cfn_model/parser/LoadBalancerV2Parser.py
cfn_model/parser/ParserError.py
cfn_model/parser/ParserRegistry.py
cfn_model/parser/PolicyDocumentParser.py
cfn_model/parser/SecurityGroupParser.py
cfn_model/parser/TransformRegistry.py
cfn_model/parser/WithPolicyDocumentParser.py
cfn_model/parser/__init__.py
cfn_model/schema/AWS_CloudFront_Distribution.yml
cfn_model/schema/AWS_EC2_Instance.yml
cfn_model/schema/AWS_EC2_NetworkInterface.yml
cfn_model/schema/AWS_EC2_NetworkInterfaceAttachment.yml
cfn_model/schema/AWS_EC2_SecurityGroup.yml
cfn_model/schema/AWS_EC2_SecurityGroupEgress.yml
cfn_model/schema/AWS_EC2_SecurityGroupIngress.yml
cfn_model/schema/AWS_ElasticLoadBalancingV2_LoadBalancer.yml
cfn_model/schema/AWS_ElasticLoadBalancing_LoadBalancer.yml
cfn_model/schema/AWS_IAM_Group.yml
cloudformation_validator-0.6.36.dist-info/METADATA
cloudformation_validator-0.6.36.dist-info/RECORD
cloudformation_validator-0.6.36.dist-info/WHEEL
cloudformation_validator-0.6.36.dist-info/entry_points.txt
cloudformation_validator-0.6.36.dist-info/top_level.txt
