Metadata-Version: 2.1
Name: cloudformation-validator
Version: 0.6.36
Summary: Lightweight, extensible schema and data validation tool for Cloudformation Templates.
Home-page: https://github.com/rubelw/cloudformation-validator
Author: Will Rubel
Author-email: willrubel@gmail.com
License: UNKNOWN
Keywords: validation,schema,dictionaries,aws,cloudformation,python,rules,linter
Platform: any
Classifier: Development Status :: 5 - Production/Stable
Classifier: Intended Audience :: Developers
Classifier: Natural Language :: English
Classifier: License :: OSI Approved :: MIT License
Classifier: Operating System :: OS Independent
Classifier: Programming Language :: Python
Classifier: Programming Language :: Python
Classifier: Programming Language :: Python :: 2
Classifier: Programming Language :: Python :: 2.6
Classifier: Programming Language :: Python :: 2.7
Classifier: Programming Language :: Python :: 3
Classifier: Programming Language :: Python :: 3.3
Classifier: Programming Language :: Python :: 3.4
Classifier: Programming Language :: Python :: 3.5
Classifier: Programming Language :: Python :: 3.6
Requires-Dist: boto3 (>=1.4.3)
Requires-Dist: requests (>=2.18)
Requires-Dist: Click (>=6.7)
Requires-Dist: PyYAML (>=3.12)
Requires-Dist: pymongo (>=3.4.0)
Requires-Dist: tabulate (>=0.8)
Requires-Dist: configparser (>=3.5.0)
Requires-Dist: jinja2 (>=2.10)
Requires-Dist: dill (>=0.2.8)
Requires-Dist: pykwalify (>=1.6.1)
Requires-Dist: schema (>=0.6.8)
Requires-Dist: future (>=0.16.0)
Requires-Dist: six (>=1.11.0)
Requires-Dist: pip
